{
   "title": "Seoul Style",
   "slug": "seoul-style",
   "author": "motoelastico",
   "authorSlug": "motoelastico",
   "storyIds": [
"http://www.bravoyourcity.com/story/beautifully-naked",
"http://www.bravoyourcity.com/story/mass-alpinism",
"http://www.bravoyourcity.com/story/gwangjang-silk-road",
"http://www.bravoyourcity.com/story/iteri-towels",
"http://www.bravoyourcity.com/story/nothing-but-tape",
"http://www.bravoyourcity.com/story/trashy-haechi",
"http://www.bravoyourcity.com/story/parking-garden",
"http://www.bravoyourcity.com/story/yellow-brushes",
"http://www.bravoyourcity.com/story/gear-it-up",
"http://www.bravoyourcity.com/story/silk-clouds",
"http://www.bravoyourcity.com/story/bike-bomb",
"http://www.bravoyourcity.com/story/cholesterol-bomb",
"http://www.bravoyourcity.com/story/house-with-roof-garden",
"http://www.bravoyourcity.com/story/frame-it",
"http://www.bravoyourcity.com/story/city-lantern-tanks-tent",
"http://www.bravoyourcity.com/story/cleaning-windows-challenge",
"http://www.bravoyourcity.com/story/open-air-gym"
   ]
}
